LICENSE
README.md
setup.py
pyhss/__init__.py
pyhss/compute.py
pyhss/factor.py
pyhss/pyhss.py
pyhss/tree.py
pyhss.egg-info/PKG-INFO
pyhss.egg-info/SOURCES.txt
pyhss.egg-info/dependency_links.txt
pyhss.egg-info/requires.txt
pyhss.egg-info/top_level.txt