Metadata-Version: 2.1
Name: pyhss
Version: 0.0.2
Summary: A python package for hierarchically semiseparable matrix representation
Home-page: https://github.com/chenxinye/pyhss.git
Author: Xinye Chen
Author-email: xinyechenai@gmail.com
Maintainer: No name
Maintainer-email: xinyechenai@gmail.com
License: MIT License
Platform: UNKNOWN
Classifier: Intended Audience :: Science/Research
Classifier: Intended Audience :: Developers
Classifier: Programming Language :: Python
Classifier: Topic :: Software Development
Classifier: Topic :: Scientific/Engineering
Classifier: Operating System :: Microsoft :: Windows
Classifier: Operating System :: Unix
Classifier: Programming Language :: Python :: 3.8
Classifier: Programming Language :: Python :: 3.9
License-File: LICENSE
